cognihub_pyeffectref/__init__.py
cognihub_pyeffectref/effect.py
cognihub_pyeffectref/helper.py
cognihub_pyeffectref/local.py
cognihub_pyeffectref/reactive_dict.py
cognihub_pyeffectref/ref.py
cognihub_pyeffectref/view.py
cognihub_pyeffectref-0.2.0.dist-info/licenses/LICENSE
cognihub_pyeffectref-0.2.0.dist-info/METADATA
cognihub_pyeffectref-0.2.0.dist-info/WHEEL
cognihub_pyeffectref-0.2.0.dist-info/top_level.txt
cognihub_pyeffectref-0.2.0.dist-info/RECORD
