Metadata-Version: 2.4
Name: cognihub-pyeffectref
Version: 0.2.0
Summary: A reactive programming library inspired by Vue 3's Composition API, featuring low-level (Ref/effect) and high-level (ReactiveDict/ReadOnlyView) interfaces
Author-email: hsz1273327 <hsz1273327@163.com>
Maintainer-email: hsz1273327 <hsz1273327@163.com>
License: MIT License
Project-URL: Homepage, https://github.com/hsz1273327/cognihub_pyeffectref
Project-URL: Repository, https://github.com/hsz1273327/cognihub_pyeffectref
Project-URL: Issues, https://github.com/hsz1273327/cognihub_pyeffectref/issues
Keywords: reactive,vue,effect,ref,cognihub,reactivedict,readonly,async,threading
Classifier: Development Status :: 4 - Beta
Classifier: Intended Audience :: Developers
Classifier: License :: OSI Approved :: MIT License
Classifier: Operating System :: OS Independent
Classifier: Programming Language :: Python :: 3
Classifier: Programming Language :: Python :: 3.10
Classifier: Programming Language :: Python :: 3.11
Classifier: Programming Language :: Python :: 3.12
Classifier: Programming Language :: Python :: 3.13
Classifier: Topic :: Software Development :: Libraries :: Python Modules
Classifier: Topic :: Software Development :: User Interfaces
Classifier: Topic :: Software Development :: Libraries :: Application Frameworks
Classifier: Typing :: Typed
Requires-Python: >=3.10
License-File: LICENSE
Provides-Extra: dev
Requires-Dist: mypy>=1.8.0; extra == "dev"
Requires-Dist: coverage>=7.3.0; extra == "dev"
Requires-Dist: build>=0.10.0; extra == "dev"
Requires-Dist: twine>=4.0.0; extra == "dev"
Provides-Extra: test
Requires-Dist: mypy>=1.8.0; extra == "test"
Requires-Dist: coverage>=7.3.0; extra == "test"
Dynamic: license-file
